[
  {
    "number": 7597,
    "action": "skipped_changed_since_review",
    "reason": "updated_at changed"
  },
  {
    "number": 7957,
    "action": "skipped_changed_since_review",
    "reason": "snapshot changed"
  },
  {
    "number": 16365,
    "action": "skipped_changed_since_review",
    "reason": "snapshot changed"
  },
  {
    "number": 17101,
    "action": "skipped_changed_since_review",
    "reason": "updated_at changed"
  },
  {
    "number": 24892,
    "action": "skipped_changed_since_review",
    "reason": "updated_at changed"
  },
  {
    "number": 28106,
    "action": "skipped_changed_since_review",
    "reason": "updated_at changed"
  },
  {
    "number": 28222,
    "action": "skipped_changed_since_review",
    "reason": "snapshot changed"
  },
  {
    "number": 29670,
    "action": "skipped_changed_since_review",
    "reason": "snapshot changed"
  },
  {
    "number": 29809,
    "action": "skipped_changed_since_review",
    "reason": "updated_at changed"
  },
  {
    "number": 31486,
    "action": "skipped_changed_since_review",
    "reason": "snapshot changed"
  },
  {
    "number": 31708,
    "action": "skipped_changed_since_review",
    "reason": "updated_at changed"
  },
  {
    "number": 33072,
    "action": "skipped_changed_since_review",
    "reason": "updated_at changed"
  },
  {
    "number": 34644,
    "action": "skipped_changed_since_review",
    "reason": "updated_at changed"
  },
  {
    "number": 34863,
    "action": "skipped_changed_since_review",
    "reason": "snapshot changed"
  },
  {
    "number": 35023,
    "action": "skipped_changed_since_review",
    "reason": "updated_at changed"
  },
  {
    "number": 37566,
    "action": "skipped_changed_since_review",
    "reason": "snapshot changed"
  },
  {
    "number": 37571,
    "action": "skipped_changed_since_review",
    "reason": "snapshot changed"
  },
  {
    "number": 37605,
    "action": "skipped_changed_since_review",
    "reason": "snapshot changed"
  },
  {
    "number": 37623,
    "action": "skipped_changed_since_review",
    "reason": "snapshot changed"
  },
  {
    "number": 37633,
    "action": "skipped_changed_since_review",
    "reason": "updated_at changed"
  },
  {
    "number": 37645,
    "action": "skipped_changed_since_review",
    "reason": "snapshot changed"
  },
  {
    "number": 37913,
    "action": "skipped_changed_since_review",
    "reason": "snapshot changed"
  },
  {
    "number": 37983,
    "action": "skipped_changed_since_review",
    "reason": "snapshot changed"
  },
  {
    "number": 38141,
    "action": "skipped_changed_since_review",
    "reason": "snapshot changed"
  },
  {
    "number": 38215,
    "action": "skipped_changed_since_review",
    "reason": "snapshot changed"
  },
  {
    "number": 38216,
    "action": "skipped_changed_since_review",
    "reason": "snapshot changed"
  },
  {
    "number": 38810,
    "action": "skipped_changed_since_review",
    "reason": "updated_at changed"
  },
  {
    "number": 39042,
    "action": "skipped_changed_since_review",
    "reason": "updated_at changed"
  },
  {
    "number": 39156,
    "action": "skipped_changed_since_review",
    "reason": "updated_at changed"
  },
  {
    "number": 39163,
    "action": "closed",
    "reason": "already implemented on main"
  },
  {
    "number": 39164,
    "action": "skipped_changed_since_review",
    "reason": "updated_at changed"
  },
  {
    "number": 39170,
    "action": "closed",
    "reason": "already implemented on main"
  },
  {
    "number": 39173,
    "action": "skipped_changed_since_review",
    "reason": "snapshot changed"
  },
  {
    "number": 39176,
    "action": "skipped_changed_since_review",
    "reason": "snapshot changed"
  },
  {
    "number": 39179,
    "action": "closed",
    "reason": "belongs on ClawHub"
  },
  {
    "number": 39180,
    "action": "closed",
    "reason": "already implemented on main"
  },
  {
    "number": 39185,
    "action": "closed",
    "reason": "already implemented on main"
  },
  {
    "number": 39187,
    "action": "closed",
    "reason": "already implemented on main"
  },
  {
    "number": 39188,
    "action": "skipped_maintainer_authored",
    "reason": "author association is MEMBER"
  },
  {
    "number": 39190,
    "action": "skipped_maintainer_authored",
    "reason": "author association is MEMBER"
  },
  {
    "number": 39191,
    "action": "skipped_maintainer_authored",
    "reason": "author association is MEMBER"
  },
  {
    "number": 39194,
    "action": "closed",
    "reason": "already implemented on main"
  },
  {
    "number": 39217,
    "action": "closed",
    "reason": "already implemented on main"
  },
  {
    "number": 39218,
    "action": "closed",
    "reason": "already implemented on main"
  },
  {
    "number": 39220,
    "action": "closed",
    "reason": "already implemented on main"
  },
  {
    "number": 39221,
    "action": "closed",
    "reason": "already implemented on main"
  },
  {
    "number": 39222,
    "action": "closed",
    "reason": "cannot reproduce on current main"
  },
  {
    "number": 39224,
    "action": "closed",
    "reason": "already implemented on main"
  },
  {
    "number": 39228,
    "action": "closed",
    "reason": "already implemented on main"
  },
  {
    "number": 39242,
    "action": "closed",
    "reason": "already implemented on main"
  },
  {
    "number": 39249,
    "action": "closed",
    "reason": "already implemented on main"
  },
  {
    "number": 39250,
    "action": "closed",
    "reason": "already implemented on main"
  },
  {
    "number": 39253,
    "action": "closed",
    "reason": "already implemented on main"
  },
  {
    "number": 39254,
    "action": "closed",
    "reason": "already implemented on main"
  },
  {
    "number": 39259,
    "action": "closed",
    "reason": "already implemented on main"
  },
  {
    "number": 39261,
    "action": "closed",
    "reason": "already implemented on main"
  },
  {
    "number": 39265,
    "action": "closed",
    "reason": "already implemented on main"
  },
  {
    "number": 39268,
    "action": "skipped_changed_since_review",
    "reason": "snapshot changed"
  },
  {
    "number": 39274,
    "action": "closed",
    "reason": "already implemented on main"
  },
  {
    "number": 39282,
    "action": "closed",
    "reason": "belongs on ClawHub"
  },
  {
    "number": 39285,
    "action": "closed",
    "reason": "already implemented on main"
  },
  {
    "number": 39288,
    "action": "closed",
    "reason": "already implemented on main"
  },
  {
    "number": 39289,
    "action": "skipped_changed_since_review",
    "reason": "updated_at changed"
  },
  {
    "number": 39295,
    "action": "closed",
    "reason": "already implemented on main"
  },
  {
    "number": 39296,
    "action": "closed",
    "reason": "belongs on ClawHub"
  },
  {
    "number": 39298,
    "action": "closed",
    "reason": "already implemented on main"
  },
  {
    "number": 39303,
    "action": "closed",
    "reason": "already implemented on main"
  },
  {
    "number": 39316,
    "action": "closed",
    "reason": "already implemented on main"
  },
  {
    "number": 39320,
    "action": "closed",
    "reason": "already implemented on main"
  },
  {
    "number": 39327,
    "action": "closed",
    "reason": "already implemented on main"
  },
  {
    "number": 39335,
    "action": "closed",
    "reason": "already implemented on main"
  },
  {
    "number": 39340,
    "action": "closed",
    "reason": "already implemented on main"
  },
  {
    "number": 39353,
    "action": "closed",
    "reason": "already implemented on main"
  },
  {
    "number": 39354,
    "action": "closed",
    "reason": "already implemented on main"
  },
  {
    "number": 39359,
    "action": "closed",
    "reason": "already implemented on main"
  },
  {
    "number": 39362,
    "action": "closed",
    "reason": "already implemented on main"
  },
  {
    "number": 39376,
    "action": "closed",
    "reason": "already implemented on main"
  },
  {
    "number": 39380,
    "action": "closed",
    "reason": "already implemented on main"
  },
  {
    "number": 39402,
    "action": "closed",
    "reason": "cannot reproduce on current main"
  },
  {
    "number": 39408,
    "action": "closed",
    "reason": "already implemented on main"
  },
  {
    "number": 39417,
    "action": "closed",
    "reason": "already implemented on main"
  },
  {
    "number": 39418,
    "action": "closed",
    "reason": "cannot reproduce on current main"
  },
  {
    "number": 39426,
    "action": "closed",
    "reason": "already implemented on main"
  },
  {
    "number": 39436,
    "action": "skipped_changed_since_review",
    "reason": "snapshot changed"
  },
  {
    "number": 39439,
    "action": "closed",
    "reason": "already implemented on main"
  },
  {
    "number": 39454,
    "action": "closed",
    "reason": "cannot reproduce on current main"
  },
  {
    "number": 39459,
    "action": "closed",
    "reason": "already implemented on main"
  },
  {
    "number": 39465,
    "action": "skipped_changed_since_review",
    "reason": "snapshot changed"
  },
  {
    "number": 39466,
    "action": "closed",
    "reason": "already implemented on main"
  },
  {
    "number": 39468,
    "action": "closed",
    "reason": "already implemented on main"
  },
  {
    "number": 39469,
    "action": "closed",
    "reason": "already implemented on main"
  },
  {
    "number": 39473,
    "action": "closed",
    "reason": "already implemented on main"
  },
  {
    "number": 39484,
    "action": "closed",
    "reason": "already implemented on main"
  },
  {
    "number": 39486,
    "action": "closed",
    "reason": "cannot reproduce on current main"
  },
  {
    "number": 39487,
    "action": "skipped_changed_since_review",
    "reason": "snapshot changed"
  },
  {
    "number": 39488,
    "action": "closed",
    "reason": "cannot reproduce on current main"
  },
  {
    "number": 39491,
    "action": "skipped_changed_since_review",
    "reason": "snapshot changed"
  },
  {
    "number": 39500,
    "action": "closed",
    "reason": "already implemented on main"
  },
  {
    "number": 39501,
    "action": "skipped_changed_since_review",
    "reason": "snapshot changed"
  },
  {
    "number": 39506,
    "action": "closed",
    "reason": "already implemented on main"
  },
  {
    "number": 39518,
    "action": "skipped_changed_since_review",
    "reason": "snapshot changed"
  },
  {
    "number": 39522,
    "action": "closed",
    "reason": "already implemented on main"
  },
  {
    "number": 39533,
    "action": "closed",
    "reason": "already implemented on main"
  },
  {
    "number": 39535,
    "action": "closed",
    "reason": "cannot reproduce on current main"
  },
  {
    "number": 39536,
    "action": "closed",
    "reason": "already implemented on main"
  },
  {
    "number": 39539,
    "action": "closed",
    "reason": "already implemented on main"
  },
  {
    "number": 39542,
    "action": "closed",
    "reason": "already implemented on main"
  },
  {
    "number": 39557,
    "action": "closed",
    "reason": "already implemented on main"
  },
  {
    "number": 39562,
    "action": "closed",
    "reason": "already implemented on main"
  },
  {
    "number": 39563,
    "action": "closed",
    "reason": "already implemented on main"
  },
  {
    "number": 39567,
    "action": "skipped_changed_since_review",
    "reason": "snapshot changed"
  },
  {
    "number": 39577,
    "action": "closed",
    "reason": "already implemented on main"
  },
  {
    "number": 39586,
    "action": "skipped_changed_since_review",
    "reason": "snapshot changed"
  },
  {
    "number": 39592,
    "action": "closed",
    "reason": "already implemented on main"
  },
  {
    "number": 39615,
    "action": "closed",
    "reason": "already implemented on main"
  },
  {
    "number": 39616,
    "action": "closed",
    "reason": "already implemented on main"
  },
  {
    "number": 39619,
    "action": "closed",
    "reason": "already implemented on main"
  },
  {
    "number": 39620,
    "action": "closed",
    "reason": "already implemented on main"
  },
  {
    "number": 39621,
    "action": "closed",
    "reason": "already implemented on main"
  },
  {
    "number": 39628,
    "action": "closed",
    "reason": "already implemented on main"
  },
  {
    "number": 39633,
    "action": "closed",
    "reason": "already implemented on main"
  },
  {
    "number": 39643,
    "action": "closed",
    "reason": "already implemented on main"
  },
  {
    "number": 39645,
    "action": "closed",
    "reason": "already implemented on main"
  },
  {
    "number": 39649,
    "action": "skipped_changed_since_review",
    "reason": "snapshot changed"
  },
  {
    "number": 39651,
    "action": "closed",
    "reason": "already implemented on main"
  },
  {
    "number": 39662,
    "action": "closed",
    "reason": "already implemented on main"
  },
  {
    "number": 39665,
    "action": "closed",
    "reason": "already implemented on main"
  },
  {
    "number": 39667,
    "action": "skipped_changed_since_review",
    "reason": "snapshot changed"
  },
  {
    "number": 39674,
    "action": "closed",
    "reason": "already implemented on main"
  },
  {
    "number": 39676,
    "action": "closed",
    "reason": "cannot reproduce on current main"
  },
  {
    "number": 39694,
    "action": "closed",
    "reason": "already implemented on main"
  },
  {
    "number": 39696,
    "action": "skipped_changed_since_review",
    "reason": "updated_at changed"
  },
  {
    "number": 39697,
    "action": "skipped_changed_since_review",
    "reason": "snapshot changed"
  },
  {
    "number": 39716,
    "action": "closed",
    "reason": "already implemented on main"
  },
  {
    "number": 39718,
    "action": "closed",
    "reason": "already implemented on main"
  },
  {
    "number": 39724,
    "action": "skipped_changed_since_review",
    "reason": "snapshot changed"
  },
  {
    "number": 39743,
    "action": "closed",
    "reason": "already implemented on main"
  },
  {
    "number": 39744,
    "action": "skipped_changed_since_review",
    "reason": "updated_at changed"
  },
  {
    "number": 39756,
    "action": "skipped_changed_since_review",
    "reason": "updated_at changed"
  },
  {
    "number": 39758,
    "action": "closed",
    "reason": "not actionable"
  },
  {
    "number": 39768,
    "action": "skipped_changed_since_review",
    "reason": "updated_at changed"
  },
  {
    "number": 39773,
    "action": "closed",
    "reason": "already implemented on main"
  },
  {
    "number": 39774,
    "action": "closed",
    "reason": "already implemented on main"
  },
  {
    "number": 39775,
    "action": "closed",
    "reason": "already implemented on main"
  },
  {
    "number": 39779,
    "action": "closed",
    "reason": "already implemented on main"
  },
  {
    "number": 39781,
    "action": "closed",
    "reason": "not actionable"
  },
  {
    "number": 39784,
    "action": "closed",
    "reason": "already implemented on main"
  },
  {
    "number": 39786,
    "action": "closed",
    "reason": "belongs on ClawHub"
  },
  {
    "number": 39791,
    "action": "closed",
    "reason": "already implemented on main"
  },
  {
    "number": 39792,
    "action": "closed",
    "reason": "already implemented on main"
  },
  {
    "number": 39793,
    "action": "closed",
    "reason": "cannot reproduce on current main"
  },
  {
    "number": 39795,
    "action": "closed",
    "reason": "already implemented on main"
  },
  {
    "number": 39799,
    "action": "closed",
    "reason": "already implemented on main"
  }
]